<?xml version="1.0" encoding="utf-8"?>
<SoundBanksInfo Platform="Mac" BasePlatform="Mac" SchemaVersion="12" SoundbankVersion="140">
	<RootPaths>
		<ProjectRoot>/Users/wmii/Library/Application Support/Wwise2019/Bottles/Wwise2019x64/dosdevices/y:/Documents/GitHub/MetroidvaniaHorrorGame/Metroidvania Horror Unity Project Settings/Assets/StreamingAssets/Audio/Metroidvania Horror Game/</ProjectRoot>
		<SourceFilesRoot>/Users/wmii/Library/Application Support/Wwise2019/Bottles/Wwise2019x64/dosdevices/y:/Documents/GitHub/MetroidvaniaHorrorGame/Metroidvania Horror Unity Project Settings/Assets/StreamingAssets/Audio/Metroidvania Horror Game/.cache/Mac/</SourceFilesRoot>
		<SoundBanksRoot>/Users/wmii/Library/Application Support/Wwise2019/Bottles/Wwise2019x64/dosdevices/y:/Documents/GitHub/MetroidvaniaHorrorGame/Metroidvania Horror Unity Project Settings/Assets/StreamingAssets/Audio/Metroidvania Horror Game/GeneratedSoundBanks/Mac/</SoundBanksRoot>
		<ExternalSourcesInputFile></ExternalSourcesInputFile>
		<ExternalSourcesOutputRoot>/Users/wmii/Library/Application Support/Wwise2019/Bottles/Wwise2019x64/dosdevices/y:/Documents/GitHub/MetroidvaniaHorrorGame/Metroidvania Horror Unity Project Settings/Assets/StreamingAssets/Audio/Metroidvania Horror Game/GeneratedSoundBanks/Mac</ExternalSourcesOutputRoot>
	</RootPaths>
	<DialogueEvents/>
	<StreamedFiles/>
	<MediaFilesNotInAnyBank/>
	<SoundBanks>
		<SoundBank Id="1054688183" Language="SFX" Hash="576066711">
			<ObjectPath>\SoundBanks\Main Menu\Main_Menu_Audio</ObjectPath>
			<ShortName>Main_Menu_Audio</ShortName>
			<Path>Main_Menu_Audio.bnk</Path>
		</SoundBank>
		<SoundBank Id="1355168291" Language="SFX" Hash="2625953151">
			<ObjectPath>Init</ObjectPath>
			<ShortName>Init</ShortName>
			<Path>Init.bnk</Path>
			<IncludedAuxBusses>
				<AuxBus Id="213475909" Name="SFX_Bus" ObjectPath="\Master-Mixer Hierarchy\Default Work Unit\Master Audio Bus\SFX_Bus"/>
				<AuxBus Id="573466488" Name="Dialogue_Bus" ObjectPath="\Master-Mixer Hierarchy\Default Work Unit\Master Audio Bus\Dialogue_Bus"/>
				<AuxBus Id="2680856269" Name="Music_Bus" ObjectPath="\Master-Mixer Hierarchy\Default Work Unit\Master Audio Bus\Music_Bus"/>
			</IncludedAuxBusses>
		</SoundBank>
		<SoundBank Id="2465958038" Language="SFX" Hash="3799066445">
			<ObjectPath>\SoundBanks\Credits\Credits_Audio</ObjectPath>
			<ShortName>Credits_Audio</ShortName>
			<Path>Credits_Audio.bnk</Path>
		</SoundBank>
		<SoundBank Id="3161908922" Language="SFX" Hash="1077138683">
			<ObjectPath>\SoundBanks\Default Work Unit\Main</ObjectPath>
			<ShortName>Main</ShortName>
			<Path>Main.bnk</Path>
		</SoundBank>
		<SoundBank Id="3558846592" Language="SFX" Hash="3062193671">
			<ObjectPath>\SoundBanks\Gameplay\Map_Area_2</ObjectPath>
			<ShortName>Map_Area_2</ShortName>
			<Path>Map_Area_2.bnk</Path>
		</SoundBank>
		<SoundBank Id="3558846593" Language="SFX" Hash="1758866869">
			<ObjectPath>\SoundBanks\Gameplay\Map_Area_3</ObjectPath>
			<ShortName>Map_Area_3</ShortName>
			<Path>Map_Area_3.bnk</Path>
		</SoundBank>
		<SoundBank Id="3558846595" Language="SFX" Hash="1683630175">
			<ObjectPath>\SoundBanks\Gameplay\Map_Area_1</ObjectPath>
			<ShortName>Map_Area_1</ShortName>
			<Path>Map_Area_1.bnk</Path>
		</SoundBank>
	</SoundBanks>
</SoundBanksInfo>
